pyconfix/__init__.py
pyconfix/__main__.py
pyconfix/core.py
pyconfix-0.10.6.dist-info/licenses/LICENSE
pyconfix-0.10.6.dist-info/METADATA
pyconfix-0.10.6.dist-info/WHEEL
pyconfix-0.10.6.dist-info/entry_points.txt
pyconfix-0.10.6.dist-info/top_level.txt
pyconfix-0.10.6.dist-info/RECORD
