Metadata-Version: 2.4
Name: pyconfix
Version: 0.10.6
Summary: A simple feature managment tool library
Home-page: https://github.com/NemesisWasAlienToo/pyconfix
Author: Nemesis
Author-email: nemesiswasalientoo@proton.me
License: MIT
Requires-Python: >=3.11
License-File: LICENSE
Requires-Dist: windows-curses; platform_system == "Windows"
Dynamic: author
Dynamic: author-email
Dynamic: description
Dynamic: description-content-type
Dynamic: home-page
Dynamic: license
Dynamic: license-file
Dynamic: requires-dist
Dynamic: requires-python
Dynamic: summary
